README.rst
setup.py
vsat/__init__.py
vsat/task.py
vsat/worker.py
vsat.egg-info/PKG-INFO
vsat.egg-info/SOURCES.txt
vsat.egg-info/dependency_links.txt
vsat.egg-info/top_level.txt